{"rwy":[["04-22","1200x40"],["14-32","830x40"]],"coords":[50.46889,13.46806],"elev":[1132,345],"code":"LKCH","circleAlt":[2130,650],"freq":[["Chomutov RADIO","123,605"]],"txt":{"cz":{"contacts":[{"phone":"+420 722 261 789","mail":"akcv@seznam.cz","name":"Aeroklub Chomutov, z.s."},{"phone":"+420 604 898 493","mail":"petr.svestka@centrum.cz","name":"Petr \u0160vestka"},{"phone":"+420 777 631 077","mail":"onje@seznam.cz","name":"Ing.Ond\u0159ej Jungmann"}],"proc":["Celn\u00ed a pasov\u00e9 odbaven\u00ed: O/R"]}},"name":"Chomutov"}