{"coords":[50.20306,12.915],"freq":[["Karlovy Vary ATIS","118,955"],["Karlovy Vary V\u011a\u017d/TOWER","121,230"],["Karlovy Vary APPROACH/RADAR","118,650"]],"rwy":[["29-11","2150x30"],["30-12","800x18"]],"name":"Karlovy Vary","elev":[1989,606],"txt":{"cz":{"proc":["Celn\u00ed a pasov\u00e9 odbaven\u00ed: Jako spr\u00e1va AD.","Je \u017e\u00e1douc\u00ed, aby letadla let\u00edc\u00ed po okruhu nep\u0159el\u00e9t\u00e1vala, pokud to lze, obydlen\u00e1 \u00fazem\u00ed obc\u00ed Ol\u0161ov\u00e1 Vrata, Kolov\u00e1 a Pila.","Velitel\u00e9 letadel VFR let\u00edc\u00edch v hladin\u00e1ch: do 3500 ft AMSL v\u010detn\u011b, mus\u00ed nejm\u00e9n\u011b 3 minuty p\u0159ed vstupem do CTR nav\u00e1zat spojen\u00ed na kan\u00e1lu KARLOVY VARY TWR 121,230, nad 3500 ft AMSL, mus\u00ed nejm\u00e9n\u011b 3 minuty p\u0159ed vstupem do TMA nav\u00e1zat spojen\u00ed na kmito\u010dtu KARLOVY VARY RADAR 118,650 MHz","V p\u0159\u00edpad\u011b, \u017ee letadlo obdr\u017e\u00ed od TWR p\u0159\u00edkaz k poj\u00ed\u017ed\u011bn\u00ed na vy\u010dk\u00e1vac\u00ed m\u00edsto RWY 29 po TWY A, velitel letadla mus\u00ed ozn\u00e1mit je\u0161t\u011b p\u0159ed zah\u00e1jen\u00edm poj\u00ed\u017ed\u011bn\u00ed, pokud nen\u00ed schopen prov\u00e9st vzlet z dr\u00e1hy 29 z k\u0159i\u017eovatky A.","P\u0159i poj\u00ed\u017ed\u011bn\u00ed na RWY 12/30 mus\u00ed pilot zastavit na vyzna\u010den\u00fdch vy\u010dk\u00e1vac\u00edch m\u00edstech a vy\u017e\u00e1dat si povolen\u00ed ke k\u0159i\u017eov\u00e1n\u00ed RWY 11/29.","P\u0159i poj\u00ed\u017ed\u011bn\u00ed z RWY 12/30 na stoj\u00e1nku si mus\u00ed pilot p\u0159ed k\u0159i\u017eov\u00e1n\u00edm RWY 11/29 vy\u017e\u00e1dat povolen\u00ed."],"contacts":[{"name":"Leti\u0161t\u011b Karlovy Vary s.r.o.","mail":"handling@airport-k-vary.cz","phone":"+420 353 360 636"},{"name":"\u00fast\u0159edna, handling","phone":"+420 353 360 611"},{"name":"\u0159editel","phone":"+420 353 360 610"},{"name":"handling p\u0159i diverz\u00edch","phone":"+420 731 195 004"},{"name":"dispe\u010dink Z\u00e1chrann\u00e9 a po\u017e\u00e1rn\u00ed slu\u017eby","phone":"+420 353 360 614"},{"name":"Bezpe\u010dnostn\u00ed dispe\u010dink (H24)","phone":"+420 353 360 618"},{"name":"provozn\u00ed dispe\u010der (zimn\u00ed \u00fadr\u017eba)","phone":"+420 731 195 016"}]}},"code":"LKKV"}